pysitemap/__init__.py
pysitemap/base_crawler.py
pysitemap/db.py
pysitemap/models.py
pysitemap/rest.py
pysitemap/validators.py
pysitemap/backends/__init__.py
pysitemap/backends/sqlite_todo.py
pysitemap/format_processors/__init__.py
pysitemap/format_processors/text.py
pysitemap/format_processors/xml.py
pysitemap/parsers/__init__.py
pysitemap/parsers/base.py
pysitemap/parsers/lxml_parser.py
pysitemap/parsers/re_parser.py
sitemap_generator-0.9.13.dist-info/LICENSE
sitemap_generator-0.9.13.dist-info/METADATA
sitemap_generator-0.9.13.dist-info/NOTICE
sitemap_generator-0.9.13.dist-info/WHEEL
sitemap_generator-0.9.13.dist-info/top_level.txt
sitemap_generator-0.9.13.dist-info/RECORD
