Metadata-Version: 2.1
Name: sitemap-generator
Version: 0.9.13
Summary: web crawler and sitemap generator.
Home-page: https://github.com/Haikson/sitemap-generator
Author: Kamo Petrosyan
Author-email: kamo@haikson.com
License: GPL3
Classifier: Environment :: Web Environment
Classifier: Intended Audience :: Developers
Classifier: License :: OSI Approved :: BSD License
Classifier: Operating System :: OS Independent
Classifier: Programming Language :: Python
Classifier: Programming Language :: Python :: 3
Classifier: Programming Language :: Python :: 3.7
Classifier: Programming Language :: Python :: 3.10
Classifier: Topic :: Software Development :: Libraries :: Python Modules
Requires: aiofile
Requires: cssselect
Requires: aiohttp
Requires: asyncio
Requires: lxml
License-File: LICENSE
License-File: NOTICE
